# CakeCTF 2022 Writeup

[yoshiking](https://twitter.com/y05h1k1ng)ã•ã‚“, [theoremoon](https://twitter.com/theoremoon)ã•ã‚“, [ptr-yudai](https://twitter.com/ptrYudai)ã•ã‚“ä¸»å‚¬ã®[CakeCTF 2022](https://2022.cakectf.com/)ã«å‚åŠ ã•ã›ã¦ã„ãŸã ãã¾ã—ãŸã€‚ã‚„ã£ã±ã‚ŠCTFã¯æ¥½ã—ã„ï¼ã¨æ€ãˆã‚‹è‰¯å•ã®æ•°ã€…ã§ã€ã™ã”ãé¢ç™½ã‹ã£ãŸã§ã™ã€‚ä¸»å‚¬ã®çš†ã•ã‚“ã€ã‚ã‚ŠãŒã¨ã†ã”ã–ã„ã¾ã—ãŸï¼ğŸ°

**è¿½è¨˜: luau (rev)ã®Third Bloodã§è³å“ã‚’ã„ãŸã ãã¾ã—ãŸã€‚ã‚ã‚ŠãŒã¨ã†ã”ã–ã„ã¾ã™ï¼**

https://twitter.com/mopisec/status/1582238950659219456

## [welcome] Welcome (676 solves)

```
Get the flag in Discord
```

å•é¡Œæ–‡ã«æ›¸ã‹ã‚Œã¦ã„ã‚‹é€šã‚Šã€Discordã‹ã‚‰FlagãŒå¾—ã‚‰ã‚Œã‚‹ã€‚

Flag: `CakeCTF{p13a53_tast3_0ur_5p3cia1_cak35}`

## [warmup / rev] nimrev (246 solves)

```
Have you ever analysed programs written in languages other than C/C++?
```

`NimMainModule` é–¢æ•°ã«ç›®ã‚’é€šã™ã¨ã€`eqStrings` ãŒå‘¼ã³å‡ºã•ã‚Œã¦ã„ã‚‹å ´æ‰€ã‚’è¦‹ã¤ã‘ã‚‹ã“ã¨ãŒã§ãã‚‹ã€‚

```
.text:000000000000AFB8                 mov     rdx, [rbp+flag]
.text:000000000000AFBC                 mov     rax, [rbp+input]
.text:000000000000AFC0                 mov     rsi, rdx
.text:000000000000AFC3                 mov     rdi, rax
.text:000000000000AFC6                 call    eqStrings
```

å…¥åŠ›ã¨ãã®ã¾ã¾æ¯”è¼ƒã—ã¦ã„ã‚‹ã“ã¨ã‹ã‚‰ã€FlagãŒ `eqStrings` ã«æ¸¡ã•ã‚Œã¦ã„ã‚‹ã¨æ¨æ¸¬ã™ã‚‹ã“ã¨ãŒã§ãã‚‹ã€‚ãƒ–ãƒ¬ãƒ¼ã‚¯ãƒã‚¤ãƒ³ãƒˆã‚’è¨­ç½®ã—ã¦å¼•æ•°ã®å†…å®¹ã‚’ç¢ºèªã™ã‚‹ã“ã¨ã§FlagãŒå¾—ã‚‰ã‚Œã‚‹ã€‚

```
gdb-peda$ x/24c 0x7ffff7d0f0e0
0x7ffff7d0f0e0: 0x43    0x61    0x6b    0x65    0x43    0x54    0x46    0x7b
0x7ffff7d0f0e8: 0x73    0x30    0x6d    0x33    0x74    0x31    0x6d    0x33
0x7ffff7d0f0f0: 0x73    0x5f    0x6e    0x30    0x74    0x5f    0x43    0x7d
```

Flag: `CakeCTF{s0m3t1m3s_n0t_C}`

## [rev] luau (64 solves)

```
Aloha! This is a luau for reverse engineerers!
```

Luaã‚½ãƒ¼ã‚¹ã‚³ãƒ¼ãƒ‰ã¨Lua 5.3ã®ãƒã‚¤ãƒˆã‚³ãƒ¼ãƒ‰ãŒé…å¸ƒã•ã‚Œã¦ã„ã‚‹ã€‚

```
libflag.lua: Lua bytecode, version 5.3
main.lua:    ASCII text
```

Luaã‚½ãƒ¼ã‚¹ã‚³ãƒ¼ãƒ‰ã‚’ç¢ºèªã—ã¦ã¿ã‚‹ã¨ã€`libflag.checkFlag` ã¨ã„ã†é–¢æ•°ãŒå‘¼ã³å‡ºã•ã‚Œã¦ãŠã‚Šã€å¼•æ•°ã¨ã—ã¦å…¥åŠ›å†…å®¹ã¨ `"CakeCTF 2022"` ã¨ã„ã†æ–‡å­—åˆ—ãŒæ¸¡ã•ã‚Œã¦ã„ã‚‹ã“ã¨ãŒã‚ã‹ã‚‹ã€‚Luaãƒã‚¤ãƒˆã‚³ãƒ¼ãƒ‰ã®ãƒ‡ã‚³ãƒ³ãƒ‘ã‚¤ãƒ©ãŒãªã„ã‹æ¢ã—ã¦ã¿ã‚‹ã¨ã€[luadec](https://github.com/viruscamp/luadec)ã¨ã„ã†ã‚‚ã®ãŒè¦‹ã¤ã‹ã£ãŸã®ã§ã€æ‰‹å…ƒã§ãƒ“ãƒ«ãƒ‰ã—ãŸä¸Šã§è©¦ã—ã¦ã¿ãŸã€‚

```sh
# luadecã‚’ãƒ“ãƒ«ãƒ‰ã™ã‚‹
$ git clone https://github.com/viruscamp/luadec
$ cd luadec
$ git submodule update --init lua-5.3
$ cd lua-5.3
$ make linux
$ cd ../luadec
$ make LUAVER=5.3

# luadecã‚’å®Ÿè¡Œã™ã‚‹
$ ./luadec ./libflag.lua
cannot find blockend > 5 , pc = 4, f->sizecode = 5
cannot find blockend > 110 , pc = 109, f->sizecode = 110
-- Decompiled using luadec 2.2 rev: 895d923 for Lua 5.3 from https://github.com/viruscamp/luadec
-- Command line: ./libflag.lua

Segmentation fault (core dumped)
```

è¦‹ã¦ã®é€šã‚Šã€æ­£å¸¸ã«ãƒ‡ã‚³ãƒ³ãƒ‘ã‚¤ãƒ«ã™ã‚‹ã“ã¨ãŒã§ããªã‹ã£ãŸã®ã§ã€é€†ã‚¢ã‚»ãƒ³ãƒ–ãƒ«æ©Ÿèƒ½ã‚’è©¦ã—ã¦ã¿ãŸã€‚

```
$ ./luadec -dis ./libflag.lua
cannot find blockend > 5 , pc = 4, f->sizecode = 5
cannot find blockend > 110 , pc = 109, f->sizecode = 110
; Disassembled using luadec 2.2 rev: 895d923 for Lua 5.3 from https://github.com/viruscamp/luadec
; Command line: -dis ./libflag.lua

; Function:        0
; Defined at line: 0
; #Upvalues:       1
; #Parameters:     0
; Is_vararg:       2
; Max Stack Size:  2

    0 [-]: CLOSURE   R0 0         ; R0 := closure(Function #0_0)
    1 [-]: NEWTABLE  R1 0 1       ; R1 := {} (size = 0,1)
    2 [-]: SETTABLE  R1 K0 R0     ; R1["checkFlag"] := R0
    3 [-]: RETURN    R1 2         ; return R1
    4 [-]: RETURN    R0 1         ; return


; Function:        0_0
; Defined at line: 1
; #Upvalues:       1
; #Parameters:     2
; Is_vararg:       0
; Max Stack Size:  41

    0 [-]: NEWTABLE  R2 26 0      ; R2 := {} (size = 26,0)
    1 [-]: LOADK     R3 K0        ; R3 := 62
    2 [-]: LOADK     R4 K1        ; R4 := 85
    3 [-]: LOADK     R5 K2        ; R5 := 25
    4 [-]: LOADK     R6 K3        ; R6 := 84
**é•·ã„ã®ã§çœç•¥**
```

ã‚¨ãƒ©ãƒ¼ã¯å…ˆã»ã©ã¨å¤‰ã‚ã‚‰ãšè¡¨ç¤ºã•ã‚Œã¦ã„ã‚‹ãŒã€æ­£å¸¸ã«é€†ã‚¢ã‚»ãƒ³ãƒ–ãƒ«ã§ãã¦ã„ã‚‹ã‚ˆã†ã«è¦‹ãˆãŸã®ã§ã€æ§‹ã‚ãšè§£æã‚’é€²ã‚ã‚‹ã“ã¨ã«ã—ãŸã€‚è¡¨ç¤ºã•ã‚ŒãŸã‚³ãƒ¼ãƒ‰ã‚’æœ€åˆã‹ã‚‰èª­ã‚“ã§ã„ãã¨ã€ã¾ãšæœ€åˆã«æ•°å€¤ã‚’R3~R40ã«ä»£å…¥ã—ã€ãã‚Œã‚’R2ã¨ã„ã†ãƒªã‚¹ãƒˆã«æ ¼ç´ã—ã¦ã„ã‚‹ã“ã¨ãŒã‚ã‹ã‚‹ã€‚

```
    1 [-]: LOADK     R3 K0        ; R3 := 62
    2 [-]: LOADK     R4 K1        ; R4 := 85
    3 [-]: LOADK     R5 K2        ; R5 := 25
.
.
.
   36 [-]: LOADK     R38 K30      ; R38 := 89
   37 [-]: LOADK     R39 K31      ; R39 := 34
   38 [-]: LOADK     R40 K31      ; R40 := 34
   39 [-]: SETLIST   R2 38 1      ; R2[0] to R2[37] := R3 to R40 ; R(a)[(c-1)*FPF+i] := R(a+i), 1 <= i <= b, a=2, b=38, c=1, FPF=50
```

æ¬¡ã«R0ï¼ˆç¬¬ä¸€å¼•æ•°ï¼‰ã¨R2ã®é•·ã•ãŒç­‰ã—ã„ã‹ç¢ºèªã™ã‚‹å‡¦ç†ãŒã‚ã‚Šã€æ›´ã«ãã®æ¬¡ã«R0ãŠã‚ˆã³R1ï¼ˆç¬¬äºŒå¼•æ•°ï¼‰ã‚’ãƒã‚¤ãƒˆã®ãƒªã‚¹ãƒˆã«å¤‰æ›ã™ã‚‹å‡¦ç†ãŒè¨˜è¿°ã•ã‚Œã¦ã„ãŸã€‚

```
   59 [-]: SETTABLE  R3 R8 R9     ; R3[R8] := R9
...
   72 [-]: SETTABLE  R4 R8 R9     ; R4[R8] := R9
```

ãã®å¾Œã€R3ãŠã‚ˆã³R4ã®é †åºã‚’é€†é †ã«ä¸¦ã³æ›¿ãˆã‚‹å‡¦ç†ã€ãã—ã¦R3ã¨R4ã§XORãƒ‡ã‚³ãƒ¼ãƒ‰ã‚’è¡Œã£ã¦ã„ã‚‹å‡¦ç†ãŒè¨˜è¿°ã•ã‚Œã¦ã„ãŸã€‚

```
   82 [-]: GETTABLE  R13 R3 R8    ; R13 := R3[R8]
   83 [-]: GETTABLE  R14 R3 R12   ; R14 := R3[R12]
   84 [-]: SETTABLE  R3 R8 R14    ; R3[R8] := R14
   85 [-]: SETTABLE  R3 R12 R13   ; R3[R12] := R13
...
   92 [-]: GETTABLE  R9 R3 R8     ; R9 := R3[R8]
   93 [-]: SUB       R10 R8 K32   ; R10 := R8 - 1
   94 [-]: LEN       R11 R4       ; R11 := #R4
   95 [-]: MOD       R10 R10 R11  ; R10 := R10 % R11
   96 [-]: ADD       R10 K32 R10  ; R10 := 1 + R10
   97 [-]: GETTABLE  R10 R4 R10   ; R10 := R4[R10]
   98 [-]: BXOR      R9 R9 R10    ; R9 := R9 ~ R10
```

ä»¥ä¸‹ãŒä¸Šè¨˜ã§åˆ¤æ˜ã—ãŸå†…å®¹ã‚’ã‚‚ã¨ã«ä½œæˆã—ãŸã‚½ãƒ«ãƒã§ã™ã€‚

```python
#!/usr/bin/env python3

r2 = [62, 85, 25, 84, 47, 56, 118, 71, 109, 0, 90, 71, 115, 9, 30, 58, 32, 101, 40, 20, 66, 111, 3, 92, 119, 22, 90, 11, 119, 35, 61, 102, 102, 115, 87, 89, 34, 34]
r4 = bytearray(b"CakeCTF 2022")

flag = ''
for i in range(len(r2)):
    flag += chr(r2[i] ^ r4[i % len(r4)])

print(flag[::-1])
```

Flag: `CakeCTF{w4n1w4n1_p4n1c_uh0uh0_g0ll1r4}`

3ç•ªç›®ã«è§£ã„ãŸã®ã§ãƒ€ãƒ¡ã‹ãªã€ã¨æ€ã„ãã‚„Prizeã‚’è²°ãˆã‚‹ã“ã¨ã«ãªã£ã¦ã€ã™ã”ãå¬‰ã—ã‹ã£ãŸã§ã™ï¼((èªå½™åŠ›......))

## [forensics / rev] zundamon (20 solves)

```
I found a suspicious process named "zundamon" running on my computer. Can you investigate the communication logs to confirm that no information has been leaked?

This program may harm your computer. Do not run it outside sandbox.
```

å®Ÿè¡Œãƒ•ã‚¡ã‚¤ãƒ« (ELF) ã¨pcapngãƒ•ã‚¡ã‚¤ãƒ«ãŒé…å¸ƒã•ã‚Œã¦ã„ã‚‹ã€‚

```
evidence.pcapng: pcapng capture file - version 1.0
zundamon:        ELF 64-bit LSB pie executable, x86-64, version 1 (SYSV), dynamically linked, interpreter /lib64/ld-linux-x86-64.so.2, BuildID[sha1]=7e0fd4acc0c6f7aed55b6aab42ccd63a2c7ee871, for GNU/Linux 3.2.0, not stripped
```

`zundamon` ã¨ã„ã†å®Ÿè¡Œãƒ•ã‚¡ã‚¤ãƒ«ã‚’è§£æã™ã‚‹ã¨ã€`/dev/input/` ä¸‹ã®ãƒ‡ãƒã‚¤ã‚¹ãƒ•ã‚¡ã‚¤ãƒ«ã‚’èª­ã¿å–ã‚Šã€ãã®å†…å®¹ã‚’ `164.70.70.9` å®›ã¦ã«é€ä¿¡ã™ã‚‹ã‚ˆã†ãªæ©Ÿèƒ½ã‚’æŒã£ã¦ã„ã‚‹ã“ã¨ãŒã‚ã‹ã‚‹ã€‚

```asm
.text:0000000000001568                 mov     rcx, cs:cmp     ; cmp
.text:000000000000156F                 lea     rdx, is_char    ; selector
.text:0000000000001576                 lea     rdi, dir        ; "/dev/input"
.text:000000000000157D                 mov     rax, fs:28h
.text:0000000000001586                 mov     [rsp+2048h+var_30], rax
.text:000000000000158E                 xor     eax, eax
.text:0000000000001590                 lea     rsi, [rsp+2048h+namelist] ; namelist
.text:0000000000001595                 call    _scandir
...
.text:0000000000001737                 lea     rdi, cp         ; "164.70.70.9"
.text:000000000000173E                 mov     [rsp+38h+var_38], 0EB180002h
.text:0000000000001745                 call    _inet_addr
...
.text:0000000000001AB8                 mov     rsi, r14        ; buf
.text:0000000000001ABB                 mov     edx, 3072       ; nbytes
.text:0000000000001AC0                 mov     edi, r12d       ; fd
.text:0000000000001AC3                 call    _read
...
.text:00000000000019EB                 mov     edx, 2          ; n
.text:00000000000019F0                 mov     rsi, r12        ; buf
.text:00000000000019F3                 mov     edi, ebp        ; fd
.text:00000000000019F5                 call    _write
```

Wiresharkã‚’ç”¨ã„ã¦ãƒšã‚¤ãƒ­ãƒ¼ãƒ‰ã‚’æŠ½å‡ºã—ãŸä¸Šã§ã€å†…å®¹ã‚’èª­ã¿ã‚„ã™ãã™ã‚‹ã‚¹ã‚¯ãƒªãƒ—ãƒˆã‚’ä½œæˆã—å®Ÿè¡Œã—ã¾ã—ãŸã€‚

```python
#!/usr/bin/env python3

import struct

KNOWN_VAR = [b'PING', b'+PONG', b'RPUSH', b'd8:f2:ca:ce:44:8d', b'*3', b'$5', b'$17', b'$3', b'*1', b'$4']

payload = bytes.fromhex(open('zundamon/payload.raw', 'r').read())
payload = payload.split(b'\r\n')
dat = []
for elem in payload:
    if elem != b'' and elem not in KNOWN_VAR and elem[0] != 58:
        dat.append(chr(elem[0]).encode())

dat = b''.join(dat)

# é•·ããªã£ãŸã®ã§ã€ä¸€éƒ¨çœç•¥ã—ã¦ã„ã¾ã™
# å®Œå…¨ç‰ˆ: https://gist.github.com/mopisec/be346d276bbc7b83be9a7c69a681bbcd

for i in range(0, len(payload), EVENT_SIZE):
    print(get_key_from_value(key_dict, struct.unpack(EVENT_FORMAT, dat[i:i+EVENT_SIZE])[0]))
```

```
$ python3 ./nanoda_solve.py
KEY_LEFTCTRL
KEY_LEFTCTRL
...
KEY_LEFTSHIFT
KEY_C
KEY_A
KEY_A
KEY_K
KEY_K
KEY_E
KEY_E
KEY_LEFTSHIFT
KEY_C
KEY_C
KEY_T
KEY_T
KEY_F
KEY_F
KEY_RIGHTBRACE
...
```

Flag: `CakeCTF{b3_C4r3fuL_0f_M4l1c10us_k3yL0gg3r}`

ã¨ã¦ã‚‚é¢ç™½ã„å•é¡Œã§ã—ãŸã€ãªã®ã ï¼ğŸ˜Š

## [survey] Survey (226 solves)

Surveyã‚’æå‡ºã™ã‚‹ã“ã¨ã§FlagãŒå¾—ã‚‰ã‚Œã‚‹ã€‚

Flag: `CakeCTF{ar3_y0u_5ati5fi3d_with_thi5_y3ar5_cak3?}`
